ovos_skills_manager/__init__.py
ovos_skills_manager/__main__.py
ovos_skills_manager/commands.py
ovos_skills_manager/config.py
ovos_skills_manager/exceptions.py
ovos_skills_manager/licenses.py
ovos_skills_manager/osm.py
ovos_skills_manager/requirements.py
ovos_skills_manager/session.py
ovos_skills_manager/skill_entry.py
ovos_skills_manager/upgrade_osm.py
ovos_skills_manager/utils.py
ovos_skills_manager/version.py
ovos_skills_manager/appstores/__init__.py
ovos_skills_manager/appstores/andlo.py
ovos_skills_manager/appstores/local.py
ovos_skills_manager/appstores/mycroft_marketplace.py
ovos_skills_manager/appstores/neon.py
ovos_skills_manager/appstores/ovos.py
ovos_skills_manager/appstores/pling.py
ovos_skills_manager/github/__init__.py
ovos_skills_manager/github/api.py
ovos_skills_manager/github/raw.py
ovos_skills_manager/github/utils.py
ovos_skills_manager/local_skill/__init__.py
ovos_skills_manager/res/AndloSkillList.jsondb
ovos_skills_manager/res/MycroftMarketplace.jsondb
ovos_skills_manager/res/Neon.jsondb
ovos_skills_manager/res/OVOS.jsondb
ovos_skills_manager/res/Pling.jsondb
ovos_skills_manager/scripts/__init__.py
ovos_skills_manager/scripts/add_auth.py
ovos_skills_manager/scripts/config_print.py
ovos_skills_manager/scripts/disable.py
ovos_skills_manager/scripts/enable.py
ovos_skills_manager/scripts/install.py
ovos_skills_manager/scripts/priority.py
ovos_skills_manager/scripts/search.py
ovos_skills_manager/scripts/sync.py
ovos_skills_manager/scripts/version.py
ovos_skills_manager-0.0.13.dist-info/LICENSE
ovos_skills_manager-0.0.13.dist-info/METADATA
ovos_skills_manager-0.0.13.dist-info/WHEEL
ovos_skills_manager-0.0.13.dist-info/entry_points.txt
ovos_skills_manager-0.0.13.dist-info/top_level.txt
ovos_skills_manager-0.0.13.dist-info/RECORD
