Metadata-Version: 2.1
Name: ovos-skills-manager
Version: 0.0.13
Summary: Open Voice OS skill manager
Home-page: https://github.com/OpenVoiceOS/ovos_skill_manager
Author: JarbasAI
Author-email: jarbasai@mailfence.com
License: Apache-2.0
License-File: LICENSE
Requires-Dist: packaging
Requires-Dist: ovos-skill-installer >=0.0.5
Requires-Dist: json-database ~=0.7
Requires-Dist: combo-lock ~=0.2
Requires-Dist: requests
Requires-Dist: requests-cache
Requires-Dist: ovos-utils ~=0.0.15
Requires-Dist: ovos-config >=0.0.3,~=0.0
Requires-Dist: pako >=0.2.3
Requires-Dist: PyYAML <7.0,>=5.4.0
Requires-Dist: bs4
Requires-Dist: click
Requires-Dist: click-default-group >=1.2.2
